LICENSE.txt
MANIFEST.in
README.rst
setup.py
src/templer/__init__.py
src/templer.django_project_app.egg-info/PKG-INFO
src/templer.django_project_app.egg-info/SOURCES.txt
src/templer.django_project_app.egg-info/dependency_links.txt
src/templer.django_project_app.egg-info/entry_points.txt
src/templer.django_project_app.egg-info/namespace_packages.txt
src/templer.django_project_app.egg-info/not-zip-safe
src/templer.django_project_app.egg-info/requires.txt
src/templer.django_project_app.egg-info/top_level.txt
src/templer/django_project_app/__init__.py
src/templer/django_project_app/structures/management_command/management/__init__.py_tmpl
src/templer/django_project_app/structures/management_command/management/commands/+model_lower+_command.py_tmpl
src/templer/django_project_app/structures/management_command/management/commands/__init__.py_tmpl
src/templer/django_project_app/templates/django_project_app/__init__.py_tmpl
src/templer/django_project_app/templates/django_project_app/admin.py_tmpl
src/templer/django_project_app/templates/django_project_app/forms.py_tmpl
src/templer/django_project_app/templates/django_project_app/models.py_tmpl
src/templer/django_project_app/templates/django_project_app/tests.py_tmpl
src/templer/django_project_app/templates/django_project_app/urls.py_tmpl
src/templer/django_project_app/templates/django_project_app/views.py_tmpl
src/templer/django_project_app/templates/django_project_app/locale/README
src/templer/django_project_app/templates/django_project_app/templates/+egg+/+model_lower+_confirm_delete.html_tmpl
src/templer/django_project_app/templates/django_project_app/templates/+egg+/+model_lower+_detail.html_tmpl
src/templer/django_project_app/templates/django_project_app/templates/+egg+/+model_lower+_form.html_tmpl
src/templer/django_project_app/templates/django_project_app/templates/+egg+/+model_lower+_list.html_tmpl
src/templer/django_project_app/templates/django_project_app/templates/+egg+/base.html_tmpl