Metadata-Version: 1.1
Name: templer.django-project-app
Version: 1.2
Summary: Templer extension for creating Django applications within projects.
Home-page: https://github.com/Fantomas42/templer.django-project-app
Author: Fantomas42
Author-email: fantomas42@gmail.com
License: BSD
Keywords: templer,django,application
Platform: UNKNOWN
Classifier: Environment :: Console
Classifier: Framework :: Django
Classifier: Intended Audience :: Developers
Classifier: License :: OSI Approved :: BSD License
Classifier: Programming Language :: Python
Classifier: Topic :: Internet :: WWW/HTTP
Classifier: Topic :: Internet :: WWW/HTTP :: Dynamic Content
Classifier: Topic :: Software Development :: Code Generators
